SQLLink/__init__.py
SQLLink/connection.py
SQLLink/db_utils.py
SQLLink/exceptions.py
SQLLink/query_builder.py
SQLLink-1.0.0.dist-info/LICENSE
SQLLink-1.0.0.dist-info/METADATA
SQLLink-1.0.0.dist-info/WHEEL
SQLLink-1.0.0.dist-info/top_level.txt
SQLLink-1.0.0.dist-info/RECORD
