Metadata-Version: 2.1
Name: SQLLink
Version: 1.0.0
Summary: SQLLink is a simple library which enables you to use SQLite databases without SQL.
Home-page: https://github.com/TRC-Loop/SQLLink
Author: AK
Author-email: ak@stellar-code.com
Classifier: Development Status :: 3 - Alpha
Classifier: Intended Audience :: Developers
Classifier: License :: OSI Approved :: MIT License
Classifier: Operating System :: OS Independent
Classifier: Programming Language :: Python :: 3
Requires-Python: >=3.6
License-File: LICENSE
Requires-Dist: sqlite3
